version_control/__init__.py
version_control/apps.py
version_control/middleware.py
version_control/utils.py
version_control/backends/__init__.py
version_control/backends/base.py
version_control/backends/bumpversion.py
version_control/backends/dummy.py
version_control/backends/gitpython.py
version_control/backends/mercurial.py
version_control/static/version_control/style.css
version_control/templates/version_control_panel.html
version_control-0.0.7.dist-info/LICENSE
version_control-0.0.7.dist-info/METADATA
version_control-0.0.7.dist-info/WHEEL
version_control-0.0.7.dist-info/top_level.txt
version_control-0.0.7.dist-info/RECORD
